{
  "record": {
    "id": "features-kinetic",
    "title": "Features   Kinetic",
    "category": "Premium",
    "sort_order": 161,
    "type": "premium",
    "types": null,
    "created_at": "2026-07-17T13:17:16.270Z",
    "page_type": "landing",
    "row_span": 1,
    "is_free": true,
    "image_preview_url": null,
    "video_preview_url": null
  },
  "result": {
    "error": null,
    "code": null,
    "prompt_text": "---\ntitle: \"Features - Kinetic\"\ncategory: Sections\nsubCategory: Features\npremium: false\nimageUrl: https://strvid.nyc3.cdn.digitaloceanspaces.com/motionitems/1783678415195-Features-Kinetic.webp\n---\n\n# Features - Kinetic\n\n```text\nAct as an award-winning UI/UX designer, master motion specialist, and elite web developer. Your objective is to recreate a hyper-premium, luxury watch brand website with absolute pixel-perfection, complex scroll-tied animations, and flawless multi-device responsiveness. \n\nThis document serves as the absolute source of truth. Every detail must be implemented exactly as described below.\n\n---\n\n## 1. Visual Design System\n\n### 1.1 Color Palette\nThe site uses a strict dark-mode luxury aesthetic with gold accents.\n- **Background (`--color-bg`)**: `#050505` (Deep space black)\n- **Text (`--color-text`)**: `#FFFFFF` (Pure white)\n- **Accent/Gold (`--color-accent` & `--color-primary-container`)**: `#C79A42` (Luxury matte gold)\n- **Muted Text (`--color-muted`)**: `#888888`\n- **Border (`--color-border`)**: `#222222`\n- **Overlay (`--color-overlay`)**: `rgba(5, 5, 5, 0.7)`\n- **Surface (`--color-surface`)**: `#111111`\n- **Surface Variant (`--color-on-surface-variant`)**: `#AAAAAA`\n\n### 1.2 Typography\n- **Heading Font (`--font-heading`)**: `'Bodoni Moda', serif` (For luxurious, high-contrast display titles)\n- **Body Font (`--font-body`)**: `'Hanken Grotesk', sans-serif` (For ultra-legible, modern sans-serif body copy)\n- **Title Sizes**: Scaled using `clamp(3rem, 6vw, 5rem)` for fluid typography.\n- **Letter Spacing**: Used heavily on navigation and uppercase accents (e.g., `letter-spacing: 4px` or `0.2em`).\n- **Line Heights**: `1.1` to `1.2` for headings, `1.5` to `1.6` for body text.\n\n---\n\n## 2. Global Layout & Grid System\n- **Maximum Width**: Constrained elements use a `max-width: 1440px` with `margin: 0 auto`.\n- **Global Padding**: `1.5rem` horizontal padding on mobile/tablet (`<=1024px`), and `2rem` on desktop (`>1024px`).\n- **Scroll Behavior**: Hidden horizontal overflow (`overflow-x: hidden`) strictly enforced on `html, body`.\n- **Box Sizing**: All elements inherit `box-sizing: border-box`.\n\n---\n\n## 3. Section-By-Section Implementation Details\n\n### 3.1 ScrollHero Section (Canvas Video Scrubbing)\n- **Architecture**: A 100vh pinned container that scrubs through a high-definition video using an HTML5 `<canvas>` element tied to the user's scroll position.\n- **Video Source**: `https://res.cloudinary.com/dprydfxok/video/upload/v1740660604/scrolling_d8p8d8.mp4`\n- **Technical Logic**:\n  - Load video and draw frames to a `100%` width, `100%` height canvas using `object-fit: cover`.\n  - Use `requestVideoFrameCallback` to sync canvas drawing with video playback.\n  - Pin the container using GSAP `ScrollTrigger` (pin duration `+=2500`).\n  - Animate an internal `frameObj.frame` tied to the scroll `scrub: 2` (smooth scrubbing).\n- **Navigation (Overlay)**:\n  - Top navigation overlapping the canvas.\n  - Desktop: Flexbox `justify-content: space-between`.\n  - Mobile (`<= 1024px`): Custom hamburger menu toggle. When open, a full-screen glassmorphism overlay (`backdrop-filter: blur(15px)`, `background: rgba(5, 5, 5, 0.95)`) slides in from `translateY(-100%)`.\n- **Loading State**: An ultra-premium \"vs-loading\" overlay (`backdrop-filter: blur(25px)`) displaying a spinning gold loader (`border-top-color: var(--color-accent)`) until the video metadata triggers `loadeddata`.\n- **Text Layers**: Sections of text (Title, description) fading in and out over the video at specific scroll percentages.\n\n### 3.2 Narrative Section\n- **Layout**: Center-aligned typography block.\n- **Padding**: `16rem 0` on desktop, `6rem 1.5rem` on mobile.\n- **Styling**: Large luxury heading with a muted, refined body text restricted to `max-width: 800px`. Includes a subtle radial background glow (`background: radial-gradient(circle, rgba(199, 154, 66, 0.05), transparent 70%)`).\n\n### 3.3 Features Section (Material Alchemy)\n- **Desktop Layout (`>1024px`)**: Grid `7fr 4fr`, `gap: 6rem`.\n- **Mobile Layout (`<=1024px`)**: Flex column `gap: 4rem`. Image wrapper naturally hugs the image (no `aspect-ratio` collapse).\n- **Image (`hhttps://res.cloudinary.com/dprydfxok/image/upload/v1782786581/w2_ih6nz9.webp`)**: Absolute positioned floating specs (`18K Rose Gold`, `Skeletonized Dial`) pinned to the image wrapper's corners, featuring a thin `border: 1px solid var(--color-border)` and microscopic backdrop blur.\n- **Content**: Clean typography lists separating \"Case\", \"Bezel\", and \"Strap\".\n\n### 3.4 Exploded View Section\n- **Layout**: Stacked center-aligned layout.\n- **Image (`https://res.cloudinary.com/dprydfxok/image/upload/v1782788684/img-2_zuiqcy.png`)**: The exploded mechanical view of the watch spanning `max-width: 800px`.\n\n### 3.5 Collection Gallery\n- **Desktop Layout (`>1024px`)**: A stunning 5-item, 6-column bento grid. \n  - Items 1 & 2: `grid-column: span 3; aspect-ratio: 4 / 3`.\n  - Items 3, 4, & 5: `grid-column: span 2; aspect-ratio: 3 / 4`.\n- **Mobile Layout (`<=1024px`)**: Single column stacking.\n- **Assets**:\n  1. `https://res.cloudinary.com/dprydfxok/image/upload/v1782786580/w1_f1ngdv.webp`\n  2. `https://res.cloudinary.com/dprydfxok/image/upload/v1782786581/w2_ih6nz9.webp`\n  3. `https://res.cloudinary.com/dprydfxok/image/upload/v1782786581/w3_gwriiw.webp`\n  4. `https://res.cloudinary.com/dprydfxok/image/upload/v1782786581/w4_ezumqb.webp`\n  5. `https://res.cloudinary.com/dprydfxok/image/upload/v1782786581/w5_t0vdxr.webp`\n- **Interactions**: On hover (`>1024px`), image scales slightly (`1.05`), text overlay fades in, and image goes from grayscale/dimmed to full vibrant color. On touch devices (`<=1024px`), text overlays are permanently visible.\n\n### 3.6 Heritage & Boutique Section\n- **Desktop Layout (`>1024px`)**: Grid `6fr 5fr`, `gap: 6rem`.\n- **Mobile Layout (`<=1024px`)**: Flex column `gap: 4rem`.\n- **Heritage Image (`https://res.cloudinary.com/dprydfxok/image/upload/v1782788683/img-3_ztdqsd.jpg`)**: Full-width object-fit cover image.\n- **Boutique Image (`https://res.cloudinary.com/dprydfxok/image/upload/v1782786901/watch-img_f0wpnt.png`)**: `aspect-ratio: 21 / 9` on desktop, shifting to `16 / 9` on mobile. Deep `filter: brightness(0.75) contrast(1.25)` applied for mood.\n\n### 3.7 Footer\n- **CTA Section**: Massive text (\"CRAFT YOUR LEGACY\") above an outlined button.\n- **Footer Bottom**: Standard flex layout, splitting a logo, navigation links, and copyright info. Stacked vertically on mobile.\n\n---\n\n## 4. Animations & Micro-Interactions\n- **GSAP ScrollTrigger**: Used comprehensively for reveal animations. Every text block and image is wrapped in an `.animate-stagger` class. \n  - Config: `y: 50, opacity: 0, duration: 1, stagger: 0.15, ease: 'power3.out'`.\n- **Context Handling**: All GSAP animations inside React `useEffect` hooks MUST be wrapped in `gsap.context()` for proper cleanup on unmounts (React 18 StrictMode safe).\n\n---\n\n## 5. Responsive Behavior & Accessibility\n- **The 1024px Breakpoint**: All layout shifts from desktop (grids, multi-columns) to mobile/tablet (single column, flex-column, hamburger menus) trigger precisely at `max-width: 1024px` to natively support iPads in portrait mode.\n- **Scroll Locking**: The canvas hero must use `width: 100%` (NOT `100vw` which causes horizontal scrollbar bugs on mobile).\n- **Accessibility**: Use semantic HTML tags (`<section>`, `<nav>`, `<main>`), proper `alt` tags for all watch images, and maintain high contrast (`#FFFFFF` on `#050505`).\n\n---\n\n## 6. Technical Stack & Architecture\n- **Framework**: React.js (Vite).\n- **Styling**: Pure CSS (No Tailwind, No CSS-in-JS). Each component maintains a corresponding `.css` file (e.g. `Features.css`, `Collection.css`).\n- **Dependencies**: \n  - `gsap` (for timelines and ScrollTrigger)\n- **Performance**: \n  - Hardware accelerated canvas drawing.\n  - Image assets utilizing highly compressed `.webp` formats.\n  - Reduced layout thrashing by avoiding CSS `aspect-ratio` on grid columns during mobile view.\n\n```\n",
    "sections": [],
    "section_names": []
  },
  "workingPrompt": {
    "mode": "premium",
    "generatedAt": "2026-07-17T13:17:16.270Z",
    "file": "working-prompt.md",
    "note": "Unlocked prompt from archive."
  }
}