{
  "record": {
    "id": "solace-sign-in",
    "title": "solace sign in",
    "category": "Premium",
    "sort_order": 395,
    "type": "premium",
    "types": null,
    "created_at": "2026-07-17T13:17:16.443Z",
    "page_type": "landing",
    "row_span": 1,
    "is_free": true,
    "image_preview_url": null,
    "video_preview_url": null
  },
  "result": {
    "error": null,
    "code": null,
    "prompt_text": "Build a fullscreen sign-in page with a **real-time liquid glass refraction effect** over a looping background video. Use React 18 + TypeScript + Tailwind CSS + Vite. Only dependency beyond React is `lucide-react`. Font: **Inter** (400, 500, 600, 700) from Google Fonts. Must be fully mobile responsive.\r\n\r\nCreate exactly 4 files: `src/LiquidGlass.tsx`, `src/FadeUp.tsx`, `src/App.tsx`, `src/index.css`.\r\n\r\n---\r\n\r\n## CRITICAL: The glass effect is NOT a CSS blur or backdrop-filter. It is a per-pixel canvas refraction engine. You MUST use the EXACT code below for `src/LiquidGlass.tsx`. Do not modify, simplify, or rewrite any of the math. Copy it verbatim:\r\n\r\n```tsx\r\nimport { useEffect, useRef } from 'react';\r\n\r\n/* eslint-disable @typescript-eslint/no-explicit-any */\r\n\r\nclass LiquidGlass {\r\n  bg: any;\r\n  opt: any;\r\n  _lut: Float32Array | null;\r\n  _lutKey: string;\r\n\r\n  constructor(bgEl: any, options: any = {}) {\r\n    this.bg = bgEl;\r\n    this.opt = Object.assign({\r\n      size: 120, shape: 'circle', rx: null,\r\n      distort: 0.06, edgeCurl: 0.04, brightness: 0.06,\r\n      specular: 0.20, border: 0.18, borderWidth: 1,\r\n      sceneW: null, sceneH: null,\r\n    }, options);\r\n    this._lut = null;\r\n    this._lutKey = '';\r\n  }\r\n\r\n  _getLUT(D: number) {\r\n    const key = `${D}:${this.opt.distort}:${this.opt.edgeCurl}`;\r\n    if (this._lut && this._lutKey === key) return this._lut;\r\n    this._lutKey = key;\r\n    const lut = new Float32Array(256);\r\n    for (let i = 0; i < 256; i++) {\r\n      const r = i / 255;\r\n      if (r < 0.7) {\r\n        lut[i] = r * (1.0 - this.opt.distort * (1 - r));\r\n      } else {\r\n        const t = (r - 0.7) / 0.3;\r\n        lut[i] = Math.min(0.985, r * (1 - this.opt.distort * (1 - r)) + t * t * this.opt.edgeCurl);\r\n      }\r\n    }\r\n    return (this._lut = lut);\r\n  }\r\n\r\n  _inShape(nx: number, ny: number, D: number) {\r\n    const { shape, rx, size } = this.opt;\r\n    if (shape === 'circle') return nx * nx + ny * ny < 1.0;\r\n    const r = (rx != null ? rx : size * 0.3) / (size / 2);\r\n    const ax = Math.abs(nx), ay = Math.abs(ny), lim = 1 - r;\r\n    if (ax > 1 || ay > 1) return false;\r\n    if (ax <= lim || ay <= lim) return true;\r\n    return (ax - lim) ** 2 + (ay - lim) ** 2 <= r * r;\r\n  }\r\n\r\n  _normR(nx: number, ny: number, D: number) {\r\n    const { shape, rx, size } = this.opt;\r\n    if (shape === 'circle') return Math.sqrt(nx * nx + ny * ny);\r\n    const r = (rx != null ? rx : size * 0.3) / (size / 2);\r\n    const ax = Math.abs(nx), ay = Math.abs(ny), lim = 1 - r;\r\n    const dx = Math.max(0, ax - lim), dy = Math.max(0, ay - lim);\r\n    const dr = Math.sqrt(dx * dx + dy * dy);\r\n    return (dr > 0 ? (lim + dr) : Math.max(ax, ay));\r\n  }\r\n\r\n  _cropBackground(cx: number, cy: number, D: number, sW: number, sH: number) {\r\n    if (!this.bg) return null;\r\n    const bw = this.bg.naturalWidth || this.bg.videoWidth;\r\n    const bh = this.bg.naturalHeight || this.bg.videoHeight;\r\n    if (!bw || !bh) return null;\r\n    const R = D / 2;\r\n    const off = document.createElement('canvas');\r\n    off.width = D; off.height = D;\r\n    const octx = off.getContext('2d')!;\r\n    octx.drawImage(this.bg,\r\n      Math.max(0, (cx - R) * (bw / sW)), Math.max(0, (cy - R) * (bh / sH)),\r\n      D * (bw / sW), D * (bh / sH),\r\n      0, 0, D, D\r\n    );\r\n    return octx.getImageData(0, 0, D, D).data;\r\n  }\r\n\r\n  _bilinear(sd: Uint8ClampedArray, x: number, y: number, D: number): [number, number, number] {\r\n    const x0 = Math.floor(x), y0 = Math.floor(y);\r\n    const x1 = Math.min(D - 1, x0 + 1), y1 = Math.min(D - 1, y0 + 1);\r\n    const fx = x - x0, fy = y - y0;\r\n    const w00 = (1 - fx) * (1 - fy), w10 = fx * (1 - fy), w01 = (1 - fx) * fy, w11 = fx * fy;\r\n    const a = (y0 * D + x0) * 4, b = (y0 * D + x1) * 4, c = (y1 * D + x0) * 4, d = (y1 * D + x1) * 4;\r\n    return [\r\n      sd[a] * w00 + sd[b] * w10 + sd[c] * w01 + sd[d] * w11,\r\n      sd[a + 1] * w00 + sd[b + 1] * w10 + sd[c + 1] * w01 + sd[d + 1] * w11,\r\n      sd[a + 2] * w00 + sd[b + 2] * w10 + sd[c + 2] * w01 + sd[d + 2] * w11,\r\n    ];\r\n  }\r\n\r\n  _drawOverlays(ctx: CanvasRenderingContext2D, D: number, R: number) {\r\n    const { shape, rx, size, specular, border, borderWidth } = this.opt;\r\n    const RX = rx != null ? rx : size * 0.3;\r\n    ctx.save();\r\n    ctx.beginPath();\r\n    shape === 'circle' ? ctx.arc(R, R, R, 0, Math.PI * 2) : ctx.roundRect(0, 0, D, D, RX);\r\n    ctx.clip();\r\n    if (specular > 0) {\r\n      const grd = ctx.createRadialGradient(R * 0.5, R * 0.28, 0, R * 0.5, R * 0.38, R * 0.45);\r\n      grd.addColorStop(0, `rgba(255,255,255,${specular})`);\r\n      grd.addColorStop(0.6, `rgba(255,255,255,${+(specular * 0.2).toFixed(3)})`);\r\n      grd.addColorStop(1, 'rgba(255,255,255,0)');\r\n      ctx.fillStyle = grd; ctx.fillRect(0, 0, D, D);\r\n    }\r\n    ctx.restore();\r\n    if (border > 0) {\r\n      const h = borderWidth / 2;\r\n      ctx.save();\r\n      ctx.strokeStyle = `rgba(255,255,255,${border})`;\r\n      ctx.lineWidth = borderWidth;\r\n      ctx.beginPath();\r\n      shape === 'circle' ? ctx.arc(R, R, R - h, 0, Math.PI * 2)\r\n        : ctx.roundRect(h, h, D - borderWidth, D - borderWidth, RX);\r\n      ctx.stroke(); ctx.restore();\r\n    }\r\n  }\r\n\r\n  render(canvas: HTMLCanvasElement, cx: number, cy: number, sW: number, sH: number) {\r\n    const D = this.opt.size, R = D / 2;\r\n    if (canvas.width !== D || canvas.height !== D) {\r\n      canvas.width = D; canvas.height = D;\r\n    }\r\n    const sd = this._cropBackground(cx, cy, D, sW, sH);\r\n    if (!sd) return false;\r\n    const lut = this._getLUT(D);\r\n    const ctx = canvas.getContext('2d')!;\r\n    const out = ctx.createImageData(D, D);\r\n    const od = out.data;\r\n    const boost = this.opt.brightness;\r\n    for (let py = 0; py < D; py++) {\r\n      for (let px = 0; px < D; px++) {\r\n        const nx = (px / R) - 1, ny = (py / R) - 1;\r\n        if (!this._inShape(nx, ny, D)) {\r\n          const i = (py * D + px) * 4; od[i] = od[i + 1] = od[i + 2] = od[i + 3] = 0; continue;\r\n        }\r\n        const normR = this._normR(nx, ny, D);\r\n        const alpha = normR > 0.93 ? Math.max(0, (1 - normR) / 0.07) : 1.0;\r\n        const theta = Math.atan2(ny, nx);\r\n        const bend = lut[Math.min(255, Math.round(normR * 255))];\r\n        const sx = Math.min(D - 1.001, Math.max(0, bend * Math.cos(theta) * R + R));\r\n        const sy = Math.min(D - 1.001, Math.max(0, bend * Math.sin(theta) * R + R));\r\n        const [rv, gv, bv] = this._bilinear(sd, sx, sy, D);\r\n        const b = (1 + boost * Math.max(0, 1 - normR * 1.6)) * 0.75;\r\n        const oi = (py * D + px) * 4;\r\n        od[oi] = Math.min(255, rv * b); od[oi + 1] = Math.min(255, gv * b);\r\n        od[oi + 2] = Math.min(255, bv * b); od[oi + 3] = Math.round(alpha * 255);\r\n      }\r\n    }\r\n    ctx.clearRect(0, 0, D, D);\r\n    ctx.putImageData(out, 0, 0);\r\n    this._drawOverlays(ctx, D, R);\r\n    return true;\r\n  }\r\n}\r\n\r\nconst GLASS_OPTIONS = {\r\n  shape: 'roundedrect' as const,\r\n  rx: 16,\r\n  distort: 0.06,\r\n  edgeCurl: 0.04,\r\n  brightness: 0.06,\r\n  specular: 0.20,\r\n  border: 0.18,\r\n  borderWidth: 1,\r\n};\r\n\r\ninterface LiquidGlassCanvasProps {\r\n  videoRef: React.RefObject<HTMLVideoElement | null>;\r\n  sceneRef: React.RefObject<HTMLDivElement | null>;\r\n  cardRef: React.RefObject<HTMLDivElement | null>;\r\n}\r\n\r\nexport default function LiquidGlassCanvas({ videoRef, sceneRef, cardRef }: LiquidGlassCanvasProps) {\r\n  const canvasRef = useRef<HTMLCanvasElement>(null);\r\n\r\n  useEffect(() => {\r\n    let glass: LiquidGlass | null = null;\r\n    let rafId: number | null = null;\r\n    let isRunning = false;\r\n\r\n    const BG_VIDEO = videoRef.current;\r\n    const SCENE_EL = sceneRef.current;\r\n    const CARD_EL = cardRef.current;\r\n    const GLASS_CV = canvasRef.current;\r\n\r\n    if (!BG_VIDEO || !SCENE_EL || !CARD_EL || !GLASS_CV) return;\r\n\r\n    function setupGlass() {\r\n      const sceneR = SCENE_EL!.getBoundingClientRect();\r\n      const cardR = CARD_EL!.getBoundingClientRect();\r\n      const W = Math.round(cardR.width);\r\n      const H = Math.round(cardR.height);\r\n      const isMobile = W < 640;\r\n      const D = isMobile ? W : Math.max(W, H);\r\n\r\n      GLASS_CV!.width = D;\r\n      GLASS_CV!.height = D;\r\n\r\n      glass = new LiquidGlass(BG_VIDEO, Object.assign({}, GLASS_OPTIONS, {\r\n        size: D,\r\n        sceneW: sceneR.width,\r\n        sceneH: sceneR.height,\r\n      }));\r\n    }\r\n\r\n    function renderLoop() {\r\n      if (!glass) return;\r\n      const sceneR = SCENE_EL!.getBoundingClientRect();\r\n      const cardR = CARD_EL!.getBoundingClientRect();\r\n      const cx = cardR.left - sceneR.left + cardR.width / 2;\r\n      const cy = cardR.top - sceneR.top + cardR.height / 2;\r\n      glass.opt.sceneW = sceneR.width;\r\n      glass.opt.sceneH = sceneR.height;\r\n      glass.render(GLASS_CV!, cx, cy, sceneR.width, sceneR.height);\r\n      rafId = requestAnimationFrame(renderLoop);\r\n    }\r\n\r\n    function startGlass() {\r\n      if (isRunning) return;\r\n      isRunning = true;\r\n      setupGlass();\r\n      renderLoop();\r\n    }\r\n\r\n    function stopGlass() {\r\n      if (rafId) cancelAnimationFrame(rafId);\r\n      rafId = null;\r\n      isRunning = false;\r\n    }\r\n\r\n    function handleResize() {\r\n      stopGlass();\r\n      setupGlass();\r\n      renderLoop();\r\n      isRunning = true;\r\n    }\r\n\r\n    BG_VIDEO.addEventListener('canplay', startGlass);\r\n    BG_VIDEO.addEventListener('playing', startGlass);\r\n\r\n    if (BG_VIDEO.readyState >= 3) startGlass();\r\n\r\n    window.addEventListener('resize', handleResize);\r\n\r\n    return () => {\r\n      stopGlass();\r\n      BG_VIDEO.removeEventListener('canplay', startGlass);\r\n      BG_VIDEO.removeEventListener('playing', startGlass);\r\n      window.removeEventListener('resize', handleResize);\r\n    };\r\n  }, [videoRef, sceneRef, cardRef]);\r\n\r\n  return (\r\n    <canvas\r\n      ref={canvasRef}\r\n      style={{\r\n        position: 'absolute',\r\n        top: 0,\r\n        left: 0,\r\n        width: '100%',\r\n        height: '100%',\r\n        display: 'block',\r\n        zIndex: 0,\r\n      }}\r\n    />\r\n  );\r\n}\r\n```\r\n\r\n---\r\n\r\n## `src/FadeUp.tsx` -- Use this exact code:\r\n\r\n```tsx\r\nimport { useEffect, useRef, useState, type ReactNode } from 'react';\r\n\r\ninterface FadeUpProps {\r\n  children: ReactNode;\r\n  delay?: number;\r\n  duration?: number;\r\n  className?: string;\r\n}\r\n\r\nexport default function FadeUp({\r\n  children,\r\n  delay = 0,\r\n  duration = 700,\r\n  className = '',\r\n}: FadeUpProps) {\r\n  const [visible, setVisible] = useState(false);\r\n  const ref = useRef<HTMLDivElement>(null);\r\n\r\n  useEffect(() => {\r\n    const timer = setTimeout(() => setVisible(true), delay);\r\n    return () => clearTimeout(timer);\r\n  }, [delay]);\r\n\r\n  return (\r\n    <div\r\n      ref={ref}\r\n      className={className}\r\n      style={{\r\n        opacity: visible ? 1 : 0,\r\n        transform: visible ? 'translateY(0)' : 'translateY(20px)',\r\n        transition: `opacity ${duration}ms cubic-bezier(0.16, 1, 0.3, 1), transform ${duration}ms cubic-bezier(0.16, 1, 0.3, 1)`,\r\n        transitionDelay: '0ms',\r\n      }}\r\n    >\r\n      {children}\r\n    </div>\r\n  );\r\n}\r\n```\r\n\r\n---\r\n\r\n## `src/index.css`\r\n\r\n```css\r\n@tailwind base;\r\n@tailwind components;\r\n@tailwind utilities;\r\n\r\n* { margin: 0; padding: 0; box-sizing: border-box; }\r\nbody {\r\n  font-family: 'Inter', sans-serif;\r\n  -webkit-font-smoothing: antialiased;\r\n  -moz-osx-font-smoothing: grayscale;\r\n}\r\n```\r\n\r\n---\r\n\r\n## `index.html` head -- Load Inter font:\r\n\r\n```html\r\n<link rel=\"preconnect\" href=\"https://fonts.googleapis.com\" />\r\n<link rel=\"preconnect\" href=\"https://fonts.gstatic.com\" crossorigin />\r\n<link href=\"https://fonts.googleapis.com/css2?family=Inter:wght@400;500;600;700&display=swap\" rel=\"stylesheet\" />\r\n<title>Solace - Login</title>\r\n```\r\n\r\n---\r\n\r\n## `src/App.tsx` -- The sign-in page layout\r\n\r\n### Structure:\r\n\r\n1. **Outermost div** (assign `sceneRef`): `relative min-h-screen w-full overflow-hidden`. Contains the video and the centered card.\r\n\r\n2. **Background video** (assign `videoRef`): `absolute inset-0 h-full w-full object-cover`, autoPlay, muted, loop, playsInline, crossOrigin=\"anonymous\".\r\n   **Video URL:** `https://d8j0ntlcm91z4.cloudfront.net/user_38xzZboKViGWJOttwIXH07lWA1P/hf_20260606_135315_5f9e8a4c-09bc-4a97-9f75-8a387d4258ee.mp4`\r\n\r\n3. **Centering wrapper:** `relative z-10 flex min-h-screen items-center justify-center px-4 py-8`.\r\n\r\n4. **Card** (assign `cardRef`): `relative w-full max-w-lg overflow-hidden rounded-2xl p-6 shadow-2xl sm:p-10 md:p-14`. No background color -- the `<LiquidGlassCanvas>` component is placed inside as the first child, acting as the card's background. All form content goes inside a `relative z-[1]` wrapper div above the canvas.\r\n\r\n### Card content (each item wrapped in `<FadeUp>` with staggered delays 0, 100, 200, ... 900ms):\r\n\r\n1. **(delay 0) Logo:** An inline SVG, 48x48, viewBox `0 0 256 256`, white fill. Path: `M 128 192 L 128 256 L 64.5 256 L 32 223 L 0 192 L 0 128 L 64 128 Z M 256 192 L 256 256 L 192.5 256 L 160 223 L 128 192 L 128 128 L 192 128 Z M 128 64 L 128 128 L 64.5 128 L 32 95 L 0 64 L 0 0 L 64 0 Z M 256 64 L 256 128 L 192.5 128 L 160 95 L 128 64 L 128 0 L 192 0 Z`. Centered, `mb-6`.\r\n\r\n2. **(delay 100) Heading:** `\"Step back in!\"` -- `text-3xl sm:text-4xl md:text-5xl font-medium tracking-tight text-center mb-2`. Text styled with `bg-gradient-to-r from-white to-purple-300 bg-clip-text text-transparent`.\r\n\r\n3. **(delay 200) Subtitle:** `\"Log in to continue your mindful exercises, calm routines, and wellness pathway\"` -- `text-xs sm:text-sm md:text-base text-white/60 leading-relaxed text-center mb-6 sm:mb-8`. A `<br>` hidden on mobile (`hidden sm:inline`).\r\n\r\n4. **(delay 300) Email field:** Label `\"Email\"` (`text-sm font-medium text-white/70 mb-1.5 block`). Input: `w-full rounded-xl border border-white/15 bg-white/5 px-4 py-3.5 text-sm text-white placeholder-white/30 outline-none transition-colors focus:border-white/30 focus:bg-white/10`. Placeholder: `\"Your email address\"`.\r\n\r\n5. **(delay 400) Password field:** Same label/input styling. Password toggle button using `Eye`/`EyeOff` from lucide-react (size 20): `absolute right-4 top-1/2 -translate-y-1/2 text-white/40 hover:text-white/70`. Placeholder: `\"Type your password\"`.\r\n\r\n6. **(delay 500) Remember/Reset row:** `flex items-center justify-between`. Left: custom checkbox using hidden input with Tailwind `peer` -- a 20x20 div (`h-5 w-5 rounded border border-white/20 bg-white/5 peer-checked:border-purple-400 peer-checked:bg-purple-500`) plus a white checkmark SVG (`absolute left-0.5 top-0.5 hidden peer-checked:block h-4 w-4`, path `M5 13l4 4L19 7` strokeWidth 3). Label `\"Stay signed in\"` (`text-sm text-white/70`). Right: `\"Reset password?\"` button (`text-sm text-white/70 hover:text-white`).\r\n\r\n7. **(delay 600) Sign In button:** `w-full rounded-full bg-white py-3.5 text-base font-semibold text-gray-900 hover:bg-white/90 active:scale-[0.98]`.\r\n\r\n8. **(delay 700) Divider:** `my-6 flex items-center gap-4` with two `h-px flex-1 bg-white/15` lines around `\"Or\"` (`text-sm text-white/40`).\r\n\r\n9. **(delay 800) Google button:** `flex w-full items-center justify-center gap-3 rounded-full border border-white/15 bg-white/5 py-3.5 text-sm font-medium text-white hover:bg-white/10 active:scale-[0.98]`. Contains the standard 4-color Google \"G\" SVG (20x20, paths with fills `#4285F4`, `#34A853`, `#FBBC05`, `#EA4335`) and text `\"Continue with Google\"`.\r\n\r\n10. **(delay 900) Join link:** `mt-6 text-center text-sm text-white/50` with `\"New to this platform?\"` and a `\"Join Now\"` button (`font-medium text-white hover:text-purple-300`).\r\n\r\n---\r\n\r\nThe entire form is wrapped in `<form className=\"space-y-5\">`. The form `onSubmit` handler calls `e.preventDefault()`.\r\n\r\n---",
    "sections": [],
    "section_names": []
  },
  "workingPrompt": {
    "mode": "premium",
    "generatedAt": "2026-07-17T13:17:16.443Z",
    "file": "working-prompt.md",
    "note": "Unlocked prompt from archive."
  }
}